fic_data_api/__init__.py
fic_data_api/api.py
fic_data_api-0.1.6.dist-info/METADATA
fic_data_api-0.1.6.dist-info/WHEEL
fic_data_api-0.1.6.dist-info/top_level.txt
fic_data_api-0.1.6.dist-info/RECORD
