Metadata-Version: 2.4
Name: fic_data_api
Version: 0.1.6
Summary: FIC数据接口
Author: FIC
Author-email: fic_server@126.com
Classifier: Programming Language :: Python :: 3
Classifier: License :: OSI Approved :: MIT License
Classifier: Operating System :: OS Independent
Requires-Dist: requests
Dynamic: author
Dynamic: author-email
Dynamic: classifier
Dynamic: requires-dist
Dynamic: summary
